vpc_control_ao/__init__.py
vpc_control_ao/settings.py
vpc_control_ao/version.py
vpc_control_ao/application/__init__.py
vpc_control_ao/application/assembler.py
vpc_control_ao/application/dto.py
vpc_control_ao/domain/__init__.py
vpc_control_ao/domain/entity.py
vpc_control_ao/domain/entity_ext.py
vpc_control_ao/domain/pipeline.py
vpc_control_ao/domain/repository.py
vpc_control_ao/domain/value_obj.py
vpc_control_ao/domain/value_obj_ext.py
vpc_control_ao/infrastructure/__init__.py
vpc_control_ao/infrastructure/ao.py
vpc_control_ao/infrastructure/converter.py
vpc_control_ao/infrastructure/do.py
vpc_control_ao/infrastructure/repository_impl.py
vpc_control_ao-0.1.14.dist-info/LICENSE
vpc_control_ao-0.1.14.dist-info/METADATA
vpc_control_ao-0.1.14.dist-info/WHEEL
vpc_control_ao-0.1.14.dist-info/top_level.txt
vpc_control_ao-0.1.14.dist-info/RECORD
